{
  "meta": {
    "generatedAt": "2025-09-25T06:49:05.846991Z",
    "note": "Translations for email-edit page.",
    "translated": true,
    "locale": "pa-IN"
  },
  "emailEdit": {
    "title": "ਈਮੇਲ ਪਤਾ",
    "description": "ਈਮੇਲ ਤੁਹਾਨੂੰ ਆਪਣੇ ਖਾਤੇ ਤੱਕ ਪਹੁੰਚ ਕਰਨ ਵਿੱਚ ਮਦਦ ਕਰਦਾ ਹੈ। ਇਹ ਹੋਰਨਾਂ ਨੂੰ ਦਿਖਾਈ ਨਹੀਂ ਦਿੰਦਾ।",
    "label": "ਈਮੇਲ",
    "verified": "ਪ੍ਰਮਾਣਿਤ",
    "placeholder": "you@example.com",
    "edit": "ਸੋਧੋ",
    "cancel": "ਰੱਦ ਕਰੋ",
    "save": "ਸੰਭਾਲੋ",
    "savedSuccess": "ਈਮੇਲ ਸਫਲਤਾਪੂਰਵਕ ਸੰਭਾਲਿਆ ਗਿਆ ਹੈ।",
    "validation": {
      "required": "ਈਮੇਲ ਲਾਜ਼ਮੀ ਹੈ।",
      "invalid": "ਕਿਰਪਾ ਕਰਕੇ ਇੱਕ ਵੈਧ ਈਮੇਲ ਪਤਾ ਦਰਜ ਕਰੋ।",
      "maxlength": "ਈਮੇਲ ਬਹੁਤ ਲੰਬਾ ਹੈ (ਵੱਧ ਤੋਂ ਵੱਧ 254 ਅੱਖਰ)।"
    }
  },
  "helpPage": {
    "title": "ਸਹਾਇਤਾ",
    "helpCenter": {
      "title": "ਸਹਾਇਤਾ ਕੇਂਦਰ",
      "description": "ਸਹਾਇਤਾ ਪ੍ਰਾਪਤ ਕਰੋ, ਅਕਸਰ ਪੁੱਛੇ ਜਾਣ ਵਾਲੇ ਪ੍ਰਸ਼ਨ ਅਤੇ ਸੰਪਰਕ ਵਿਕਲਪ।"
    },
    "terms": {
      "title": "ਸ਼ਰਤਾਂ ਅਤੇ ਗੋਪਨੀਯਤਾ ਨੀਤੀ",
      "description": "ਸਾਡੀਆਂ ਸ਼ਰਤਾਂ ਅਤੇ ਡੇਟਾ ਨੀਤੀ ਪੜ੍ਹੋ।"
    },
    "channelReports": {
      "title": "ਚੈਨਲ ਰਿਪੋਰਟਸ",
      "description": "ਰਿਪੋਰਟਾਂ ਪ੍ਰਬੰਧਤ ਅਤੇ ਵੇਖੋ।"
    },
    "appInfo": {
      "title": "ਐਪ ਜਾਣਕਾਰੀ",
      "description": "ਵਰਜ਼ਨ, ਕਾਨੂੰਨੀ ਅਤੇ ਤਕਨੀਕੀ ਵੇਰਵੇ।"
    }
  },"common": {
    "ok": "ਠੀਕ ਹੈ",
    "cancel": "ਰੱਦ ਕਰੋ",
    "logout": "ਲਾੱਗ ਆਉਟ"
  },
  "settingsPage": {
    "title": "ਸੈਟਿੰਗਜ਼",
    "account": { "title": "ਖਾਤਾ", "description": "ਪ੍ਰਾਈਵੇਸੀ, ਸੁਰੱਖਿਆ, ਨੰਬਰ ਬਦਲੋ" },
    "privacy": { "title": "ਪ੍ਰਾਈਵੇਸੀ", "description": "ਆਪਣੀਆਂ ਪ੍ਰਾਈਵੇਸੀ ਸੈਟਿੰਗਜ਼ ਕੰਟਰੋਲ ਕਰੋ" },
    "avatar": { "title": "ਅਵਤਾਰ", "description": "ਪ੍ਰੋਫਾਈਲ ਤਸਵੀਰ ਬਦਲੋ" },
    "chats": { "title": "ਚੈਟਾਂ", "description": "ਥੀਮ, ਵਾਲਪੇਪਰ, ਬੈਕਅੱਪ" },
    "accessibility": { "title": "ਪਹੁੰਚਯੋਗਤਾ", "description": "ਲਿਖਤ ਦਾ ਆਕਾਰ ਅਤੇ ਪ੍ਰਦਰਸ਼ਨ ਵਿਕਲਪ" },
    "notifications": { "title": "ਨੋਟੀਫਿਕੇਸ਼ਨ", "description": "ਸੁਨੇਹੇ, ਸਮੂਹ ਅਤੇ ਕਾਲ ਅਲਰਟ" },
    "storage": { "title": "ਸਟੋਰੇਜ ਅਤੇ ਡਾਟਾ", "description": "ਸਟੋਰੇਜ ਅਤੇ ਨੈੱਟਵਰਕ ਵਰਤੋਂ ਪ੍ਰਬੰਧਿਤ ਕਰੋ" },
    "appLanguage": { "title": "ਐਪ ਭਾਸ਼ਾ", "description": "ਐਪ ਭਾਸ਼ਾ ਚੁਣੋ" },
    "help": { "title": "ਮਦਦ ਅਤੇ ਫੀਡਬੈਕ", "description": "ਮਦਦ ਕੇਂਦਰ, ਸਾਡੇ ਨਾਲ ਸੰਪਰਕ ਕਰੋ, ਐਪ ਜਾਣਕਾਰੀ" },
    "updates": { "title": "ਐਪ ਅੱਪਡੇਟ", "description": "ਅੱਪਡੇਟ ਚੈੱਕ ਕਰੋ, ਆਟੋਮੈਟਿਕ ਅੱਪਡੇਟ" },
    "invite": { "title": "ਦੋਸਤ ਨੂੰ ਸੱਦਾ ਦਿਓ", "description": "ਐਪ ਸੰਪਰਕਾਂ ਨਾਲ ਸਾਂਝੀ ਕਰੋ" },
    "logout": {
      "title": "ਲਾੱਗ ਆਉਟ",
      "description": "ਐਪ ਡਾਟਾ ਸਾਫ ਕਰੋ ਅਤੇ ਸਾਈਨ ਆਉਟ ਕਰੋ",
      "confirmHeader": "ਲਾੱਗ ਆਉਟ ਦੀ ਪੁਸ਼ਟੀ ਕਰੋ",
      "confirmMessage": "ਕੀ ਤੁਸੀਂ ਯਕੀਨੀ ਤੌਰ 'ਤੇ ਲਾੱਗ ਆਉਟ ਕਰਨਾ ਅਤੇ ਐਪ ਡਾਟਾ ਸਾਫ ਕਰਨਾ ਚਾਹੁੰਦੇ ਹੋ?",
      "loadingHeader": "ਲਾੱਗ ਆਉਟ ਕੀਤਾ ਜਾ ਰਿਹਾ ਹੈ",
      "loadingMessage": "ਕਿਰਪਾ ਕਰਕੇ ਉਡੀਕ ਕਰੋ...",
      "successHeader": "ਲਾੱਗ ਆਉਟ ਹੋ ਗਿਆ",
      "successMessage": "ਤੁਸੀਂ ਸਫਲਤਾਪੂਰਵਕ ਲਾੱਗ ਆਉਟ ਕਰ ਦਿੱਤਾ ਹੈ।"
    },
    "defaultStatus": "ਉਪਲਬਧ"
  }
}
